COPYING
MANIFEST.in
README
changelog.txt
setup.py
Helmholtz.egg-info/PKG-INFO
Helmholtz.egg-info/SOURCES.txt
Helmholtz.egg-info/dependency_links.txt
Helmholtz.egg-info/top_level.txt
doc/Makefile
doc/all_diagrams.mwb
doc/component_overview.txt
doc/components.txt
doc/conf.py
doc/contact.txt
doc/deployment.txt
doc/er_diagram_access_control.pdf
doc/er_diagram_core_acquisition.pdf
doc/er_diagram_drugs_acquisition.pdf
doc/er_diagram_management.pdf
doc/er_diagram_methods_acquisition.pdf
doc/er_diagram_preparation_acquisition.pdf
doc/er_diagram_signal_acquisition.pdf
doc/getting_started.txt
doc/index.txt
doc/overview.txt
doc/populating.txt
doc/proposed_apps.txt
doc/settings.txt
doc/components/access_control.txt
doc/components/analysis.txt
doc/components/annotation.txt
doc/components/cells.txt
doc/components/chemistry.txt
doc/components/core.txt
doc/components/drug_applications.txt
doc/components/electrophysiology.txt
doc/components/equipment.txt
doc/components/experiments.txt
doc/components/histochemistry.txt
doc/components/location.txt
doc/components/measurements.txt
doc/components/neuralstructures.txt
doc/components/people.txt
doc/components/preparations.txt
doc/components/reconstruction.txt
doc/components/recording.txt
doc/components/signals.txt
doc/components/species.txt
doc/components/stimulation.txt
doc/components/storage.txt
doc/components/trackers.txt
doc/components/units.txt
helmholtz/__init__.py
helmholtz/urls.py
helmholtz/views.py
helmholtz/access_control/__init__.py
helmholtz/access_control/admin.py
helmholtz/access_control/backends.py
helmholtz/access_control/decorators.py
helmholtz/access_control/forms.py
helmholtz/access_control/middleware.py
helmholtz/access_control/models.py
helmholtz/access_control/overload.py
helmholtz/access_control/urls.py
helmholtz/access_control/views.py
helmholtz/access_control/templates/access_control.html
helmholtz/access_control/templates/login.html
helmholtz/access_control/templates/permission_denied.html
helmholtz/access_control/templates/registration/login.html
helmholtz/access_control/templates/registration/password_reset_confirm.html
