Metadata-Version: 1.0
Name: Helmholtz
Version: 0.2.0
Summary: A framework for creating neuroscience databases
Home-page: http://www.dbunic.cnrs-gif.fr/helmholtz/
Author: Neuroinformatics research group, UNIC, CNRS
Author-email: andrew.davison@unic.cnrs-gif.fr
License: CeCILL http://www.cecill.info
Keywords: neuroscience database Django metadata
Platform: UNKNOWN
Classifier: Development Status :: 3 - Alpha
Classifier: Environment :: Web Environment
Classifier: Intended Audience :: Science/Research
Classifier: License :: Other/Proprietary License
Classifier: Natural Language :: English
Classifier: Operating System :: OS Independent
Classifier: Programming Language :: Python
Classifier: Framework :: Django
Classifier: Topic :: Scientific/Engineering
Classifier: Topic :: Database
